CHANGELOG.rst
MANIFEST.in
README.rst
setup.py
pycnik/__init__.py
pycnik/model.py
pycnik/pycnik.py
pycnik.egg-info/PKG-INFO
pycnik.egg-info/SOURCES.txt
pycnik.egg-info/dependency_links.txt
pycnik.egg-info/entry_points.txt
pycnik.egg-info/requires.txt
pycnik.egg-info/top_level.txt
test/test_copy.py
test/test_datasource.py
test/test_layers.py
test/test_map.py
test/test_metawriter.py
test/test_style.py