Metadata-Version: 1.1
Name: pycnik
Version: 1.4
Summary: Tool for generating Mapnik's stylesheets from python code
Home-page: https://github.com/Mappy/pycnik.git
Author: Ludovic Delauné
Author-email: ludovic.delaune@mappy.com
License: UNKNOWN
Platform: UNKNOWN
Classifier: Development Status :: 5 - Production/Stable
Classifier: Environment :: Web Environment
Classifier: Intended Audience :: Developers
Classifier: Intended Audience :: Science/Research
Classifier: Operating System :: OS Independent
Classifier: Programming Language :: Python
Classifier: Topic :: Internet :: WWW/HTTP :: Dynamic Content
Classifier: Topic :: Utilities
